cadnano2/__init__.py
cadnano2/cadnano.py
cadnano2/cadnanoqt.py
cadnano2/main.py
cadnano2/spCadNano.py
cadnano2/util.py
cadnano2/controllers/__init__.py
cadnano2/controllers/documentcontroller.py
cadnano2/controllers/viewrootcontroller.py
cadnano2/controllers/itemcontrollers/__init__.py
cadnano2/controllers/itemcontrollers/activesliceitemcontroller.py
cadnano2/controllers/itemcontrollers/partitemcontroller.py
cadnano2/controllers/itemcontrollers/virtualhelixitemcontroller.py
cadnano2/controllers/itemcontrollers/strand/__init__.py
cadnano2/controllers/itemcontrollers/strand/abstractstranditemcontroller.py
cadnano2/controllers/itemcontrollers/strand/endpointitemcontroller.py
cadnano2/controllers/itemcontrollers/strand/stranditemcontroller.py
cadnano2/controllers/itemcontrollers/strand/xoveritemcontroller.py
cadnano2/controllers/mayacontrollers/__init__.py
cadnano2/controllers/mayacontrollers/helixManip.py
cadnano2/controllers/mayacontrollers/mayaObjectManager.py
cadnano2/controllers/mayacontrollers/mayaSelectionContex.py
cadnano2/controllers/mayacontrollers/removedMsgCmd.py
cadnano2/data/__init__.py
cadnano2/data/dnasequences.py
cadnano2/dummyqt/QtCore.py
cadnano2/dummyqt/QtGui.py
cadnano2/dummyqt/__init__.py
cadnano2/include/__init__.py
cadnano2/include/fetchfile.py
cadnano2/include/getdependencies.py
cadnano2/model/__init__.py
cadnano2/model/document.py
cadnano2/model/enum.py
cadnano2/model/oligo.py
cadnano2/model/strand.py
cadnano2/model/strandset.py
cadnano2/model/virtualhelix.py
cadnano2/model/decorators/__init__.py
cadnano2/model/decorators/decorator.py
cadnano2/model/decorators/insertion.py
cadnano2/model/decorators/modifier.py
cadnano2/model/io/__init__.py
cadnano2/model/io/decoder.py
cadnano2/model/io/encoder.py
cadnano2/model/io/legacydecoder.py
cadnano2/model/io/legacyencoder.py
cadnano2/model/parts/__init__.py
cadnano2/model/parts/honeycombpart.py
cadnano2/model/parts/part.py
cadnano2/model/parts/squarepart.py
cadnano2/osx/CNApplicationDelegate.py
cadnano2-2.4.12.dist-info/LICENSE
cadnano2-2.4.12.dist-info/METADATA
cadnano2-2.4.12.dist-info/WHEEL
cadnano2-2.4.12.dist-info/entry_points.txt
cadnano2-2.4.12.dist-info/top_level.txt
cadnano2-2.4.12.dist-info/RECORD
