Metadata-Version: 2.2
Name: cadnano2
Version: 2.4.12
Summary: Cadnano2 for PyQt6
Home-page: https://github.com/douglaslab/cadnano2
Author: Shawn Douglas
Author-email: Shawn Douglas <shawn.douglas@ucsf.edu>
License: MIT
Classifier: Development Status :: 4 - Beta
Classifier: Intended Audience :: Science/Research
Classifier: License :: OSI Approved :: MIT License
Classifier: Operating System :: OS Independent
Classifier: Programming Language :: Python :: 3
Requires-Python: >=3.8
License-File: LICENSE
Requires-Dist: PyQt6
Dynamic: author
Dynamic: home-page
